pysmaz2/__init__.py
pysmaz2/backends/__init__.py
pysmaz2/backends/cffi/_smaz2.pypy310-pp73-aarch64-linux-gnu.so
pysmaz2/backends/cffi/__init__.py
pysmaz2/backends/cffi/build.py
pysmaz2/backends/cython/_smaz2.pypy310-pp73-aarch64-linux-gnu.so
pysmaz2/backends/cython/_smaz2.c
pysmaz2/backends/cython/__init__.py
pysmaz2-0.0.3.dist-info/RECORD
pysmaz2-0.0.3.dist-info/METADATA
pysmaz2-0.0.3.dist-info/WHEEL
pysmaz2-0.0.3.dist-info/top_level.txt
