Metadata-Version: 2.1
Name: pysmaz2
Version: 0.0.3
Summary: python binding for smaz2
Home-page: https://github.com/synodriver/pysmaz2
Author: synodriver
Author-email: diguohuangjiajinweijun@gmail.com
License: BSD
Keywords: smaz2,compress,decompress
Classifier: Development Status :: 4 - Beta
Classifier: Operating System :: OS Independent
Classifier: License :: OSI Approved :: BSD License
Classifier: Programming Language :: C
Classifier: Programming Language :: Cython
Classifier: Programming Language :: Python
Classifier: Programming Language :: Python :: 3.8
Classifier: Programming Language :: Python :: 3.9
Classifier: Programming Language :: Python :: 3.10
Classifier: Programming Language :: Python :: 3.11
Classifier: Programming Language :: Python :: 3.12
Classifier: Programming Language :: Python :: Implementation :: CPython
Classifier: Programming Language :: Python :: Implementation :: PyPy
Requires-Python: >=3.6
Requires-Dist: cffi >=1.0.0
